Topsis/Topsis_Sidharth.py
Topsis/__init__.py
topsis_sidharth_102017016-1.0.0.dist-info/METADATA
topsis_sidharth_102017016-1.0.0.dist-info/WHEEL
topsis_sidharth_102017016-1.0.0.dist-info/top_level.txt
topsis_sidharth_102017016-1.0.0.dist-info/RECORD
