Metadata-Version: 2.1
Name: topsis-sidharth-102017016
Version: 1.0.0
Summary: Topsis package
Author: Sidharth Bahl
Author-email: <bahlsidharth@gmail.com>
License: UNKNOWN
Keywords: python,topsis,data science,data analysis
Platform: UNKNOWN
Classifier: Development Status :: 1 - Planning
Classifier: Intended Audience :: Developers
Classifier: Programming Language :: Python :: 3
Classifier: Operating System :: Unix
Classifier: Operating System :: MacOS :: MacOS X
Classifier: Operating System :: Microsoft :: Windows
Requires-Dist: pandas
Requires-Dist: numpy
